reader/__init__.py
reader/__main__.py
reader/config.toml
reader/feed.py
reader/viewer.py
lauris_real_python_reader-1.0.1.dist-info/LICENSE
lauris_real_python_reader-1.0.1.dist-info/METADATA
lauris_real_python_reader-1.0.1.dist-info/WHEEL
lauris_real_python_reader-1.0.1.dist-info/entry_points.txt
lauris_real_python_reader-1.0.1.dist-info/top_level.txt
lauris_real_python_reader-1.0.1.dist-info/RECORD
