Metadata-Version: 2.1
Name: lauris-real-python-reader
Version: 1.0.1
Summary: Read the latest Real Python tutorials
Author-email: Damocles <damocles@gmail.com>
License: MIT License        
Project-URL: Homepage, https://github.com/realpython/reader
Keywords: feed,reader,tutorial
Classifier: License :: OSI Approved :: MIT License
Classifier: Programming Language :: Python
Classifier: Programming Language :: Python :: 3
Requires-Python: >=3.9
License-File: LICENSE
Requires-Dist: feedparser (>=5.2.0)
Requires-Dist: html2text
Requires-Dist: tomli ; python_version < "3.11"
Provides-Extra: dev
Requires-Dist: black ; extra == 'dev'
Requires-Dist: bumpver ; extra == 'dev'
Requires-Dist: isort ; extra == 'dev'
Requires-Dist: pip-tools ; extra == 'dev'
Requires-Dist: pytest ; extra == 'dev'
